stix_shifter_modules/proxy/__init__.py
stix_shifter_modules/proxy/entry_point.py
stix_shifter_modules/proxy/configuration/config.json
stix_shifter_modules/proxy/configuration/dialects.json
stix_shifter_modules/proxy/configuration/lang_en.json
stix_shifter_modules/proxy/stix_translation/__init__.py
stix_shifter_modules/proxy/stix_translation/json_to_stix_translator.py
stix_shifter_modules/proxy/stix_translation/query_translator.py
stix_shifter_modules/proxy/stix_translation/results_translator.py
stix_shifter_modules/proxy/stix_translation/utils.py
stix_shifter_modules/proxy/stix_transmission/__init__.py
stix_shifter_modules/proxy/stix_transmission/connector.py
stix_shifter_modules_proxy-8.0.2.dist-info/licenses/AUTHORS.md
stix_shifter_modules_proxy-8.0.2.dist-info/licenses/LICENSE.md
stix_shifter_modules_proxy-8.0.2.dist-info/licenses/NOTICE
stix_shifter_modules_proxy-8.0.2.dist-info/METADATA
stix_shifter_modules_proxy-8.0.2.dist-info/WHEEL
stix_shifter_modules_proxy-8.0.2.dist-info/top_level.txt
stix_shifter_modules_proxy-8.0.2.dist-info/RECORD
